eskiz/__init__.py
eskiz/api.py
eskiz/types/__init__.py
eskiz/types/base.py
eskiz/types/enums.py
eskiz/types/sms.py
eskiz/types/template.py
eskiz/types/token.py
eskiz/types/user.py
eskiz/utils/__init__.py
eskiz/utils/exceptions.py
eskiz/utils/fields.py
eskiz/utils/message.py
eskiz/utils/methods.py
eskiz_sms_client-1.0.5.dist-info/LICENSE
eskiz_sms_client-1.0.5.dist-info/METADATA
eskiz_sms_client-1.0.5.dist-info/WHEEL
eskiz_sms_client-1.0.5.dist-info/RECORD
