Metadata-Version: 2.3
Name: eskiz-sms-client
Version: 1.0.5
Summary: Async Python SDK of Eskiz.uz SMS Gateway
License: MIT
Keywords: eskiz-sms,eskiz,eskiz-sms-client,eskiz.uz
Author: hoosnick
Author-email: hoosnick000@gmail.com
Requires-Python: >=3.9,<4.0
Classifier: Development Status :: 4 - Beta
Classifier: Intended Audience :: Developers
Classifier: License :: OSI Approved :: MIT License
Classifier: Programming Language :: Python :: 3
Classifier: Programming Language :: Python :: 3.9
Classifier: Programming Language :: Python :: 3.10
Classifier: Programming Language :: Python :: 3.11
Classifier: Programming Language :: Python :: 3.12
Classifier: Programming Language :: Python :: 3.13
Classifier: Topic :: Software Development :: Build Tools
Provides-Extra: ujson
Requires-Dist: aiohttp (>=3.9.3)
Requires-Dist: attrs (>=23.2.0)
Requires-Dist: certifi (>=2024.2.2)
Requires-Dist: pydantic (>=2.6.2)
Requires-Dist: pyjwt (>=2.8.0)
Requires-Dist: ujson (>=5.9.0) ; extra == "ujson"
Project-URL: Bug Tracker, https://github.com/old-juniors/eskiz-sms/issues
Project-URL: Source, https://github.com/old-juniors/eskiz-sms
